odoo/addons/stock_available_mrp/README.rst
odoo/addons/stock_available_mrp/__init__.py
odoo/addons/stock_available_mrp/__manifest__.py
odoo/addons/stock_available_mrp/data/ir_config_parameter.xml
odoo/addons/stock_available_mrp/demo/mrp_data.xml
odoo/addons/stock_available_mrp/i18n/ca.po
odoo/addons/stock_available_mrp/i18n/de.po
odoo/addons/stock_available_mrp/i18n/es.po
odoo/addons/stock_available_mrp/i18n/fi.po
odoo/addons/stock_available_mrp/i18n/fr.po
odoo/addons/stock_available_mrp/i18n/hr_HR.po
odoo/addons/stock_available_mrp/i18n/it.po
odoo/addons/stock_available_mrp/i18n/pt_BR.po
odoo/addons/stock_available_mrp/i18n/sl.po
odoo/addons/stock_available_mrp/i18n/stock_available_mrp.pot
odoo/addons/stock_available_mrp/i18n/zh_CN.po
odoo/addons/stock_available_mrp/migrations/17.0.1.0.0/pre-migration.py
odoo/addons/stock_available_mrp/models/__init__.py
odoo/addons/stock_available_mrp/models/product_product.py
odoo/addons/stock_available_mrp/models/res_config_settings.py
odoo/addons/stock_available_mrp/readme/CONTRIBUTORS.md
odoo/addons/stock_available_mrp/readme/DESCRIPTION.md
odoo/addons/stock_available_mrp/readme/ROADMAP.md
odoo/addons/stock_available_mrp/static/description/icon.png
odoo/addons/stock_available_mrp/static/description/index.html
odoo/addons/stock_available_mrp/tests/__init__.py
odoo/addons/stock_available_mrp/tests/test_potential_qty.py
odoo/addons/stock_available_mrp/views/res_config_settings_views.xml
odoo_addon_stock_available_mrp-17.0.1.1.0.dist-info/METADATA
odoo_addon_stock_available_mrp-17.0.1.1.0.dist-info/WHEEL
odoo_addon_stock_available_mrp-17.0.1.1.0.dist-info/top_level.txt
odoo_addon_stock_available_mrp-17.0.1.1.0.dist-info/RECORD
