Metadata-Version: 2.1
Name: odoo-addon-stock_available_mrp
Version: 17.0.1.1.0
Requires-Python: >=3.10
Requires-Dist: odoo-addon-stock_available>=17.0dev,<17.1dev
Requires-Dist: odoo>=17.0a,<17.1dev
Summary: Consider the production potential is available to promise
Home-page: https://github.com/OCA/stock-logistics-availability
License: AGPL-3
Author: =?utf-8?q?Num=C3=A9rigraphe=2COdoo_Community_Association_=28OCA=29?=
Author-email: support@odoo-community.org
Classifier: Programming Language :: Python
Classifier: Framework :: Odoo
Classifier: Framework :: Odoo :: 17.0
Classifier: License :: OSI Approved :: GNU Affero General Public License v3
